tukaan/__init__.py
tukaan/_base.py
tukaan/_collect.py
tukaan/_events.py
tukaan/_images.py
tukaan/_keysyms.py
tukaan/_layout.py
tukaan/_misc.py
tukaan/_mixins.py
tukaan/_props.py
tukaan/_system.py
tukaan/_tcl.py
tukaan/_utils.py
tukaan/_variables.py
tukaan/app.py
tukaan/clipboard.py
tukaan/colors.py
tukaan/enums.py
tukaan/exceptions.py
tukaan/screen.py
tukaan/time.py
tukaan/timeouts.py
tukaan/a11y/a11y.py
tukaan/dialogs/__init__.py
tukaan/dialogs/aboutdialog.py
tukaan/dialogs/colorpicker.py
tukaan/dialogs/datetimedialogs.py
tukaan/dialogs/dialog.py
tukaan/dialogs/filedialog.py
tukaan/dialogs/fontpicker.py
tukaan/dialogs/inputdialog.py
tukaan/dialogs/messagebox.py
tukaan/dialogs/notification.py
tukaan/fonts/font.py
tukaan/fonts/fontfile.py
tukaan/theming/__init__.py
tukaan/theming/aqua.tcl
tukaan/theming/clam.tcl
tukaan/theming/kolorscheme.py
tukaan/theming/kolorscheme.tcl
tukaan/theming/lookandfeel.py
tukaan/theming/themes.py
tukaan/theming/win32.tcl
tukaan/widgets/button.py
tukaan/widgets/checkbox.py
tukaan/widgets/combobox.py
tukaan/widgets/frame.py
tukaan/widgets/label.py
tukaan/widgets/progressbar.py
tukaan/widgets/radiobutton.py
tukaan/widgets/scrollbar.py
tukaan/widgets/separator.py
tukaan/widgets/slider.py
tukaan/widgets/spinbox.py
tukaan/widgets/splitview.py
tukaan/widgets/tabview.py
tukaan/widgets/textbox.py
tukaan/widgets/tooltip.py
tukaan/windows/main_window.py
tukaan/windows/window.py
tukaan/windows/wm.py
tukaan-0.2.1.dist-info/LICENSE
tukaan-0.2.1.dist-info/METADATA
tukaan-0.2.1.dist-info/WHEEL
tukaan-0.2.1.dist-info/top_level.txt
tukaan-0.2.1.dist-info/RECORD
