Metadata-Version: 2.1
Name: tukaan
Version: 0.2.1
Summary: A modern, cross platform Python toolkit for creating desktop GUI applications.
Home-page: https://tukaan.github.io
Author: rdbende
Author-email: rdbende@gmail.com
License: MIT license
Project-URL: Documentation, https://tukaan.github.io/docs
Project-URL: Source, https://github.com/tukaan/tukaan
Project-URL: Tracker, https://github.com/tukaan/tukaan/issues
Keywords: gui,tcl,tcl/tk,tk,tkinter,ttk,tukaan,ui
Platform: UNKNOWN
Classifier: Development Status :: 2 - Pre-Alpha
Classifier: Intended Audience :: Developers
Classifier: License :: OSI Approved :: MIT License
Classifier: Operating System :: OS Independent
Classifier: Programming Language :: Python :: 3 :: Only
Classifier: Programming Language :: Python :: 3.7
Classifier: Programming Language :: Python :: 3.8
Classifier: Programming Language :: Python :: 3.9
Classifier: Programming Language :: Python :: 3.10
Classifier: Programming Language :: Python :: 3.11
Classifier: Programming Language :: Tcl
Classifier: Programming Language :: C
Classifier: Programming Language :: C++
Classifier: Typing :: Typed
Requires-Python: >=3.7
License-File: LICENSE
Requires-Dist: pillow (>=8.0.0)
Requires-Dist: screeninfo (>=0.8)
Requires-Dist: typing-extensions (>=4.3.0) ; python_version < "3.9"
Requires-Dist: libtukaan-mac (==0.1.2) ; sys_platform == "darwin"
Requires-Dist: libtukaan-unix (==0.1.2) ; sys_platform == "linux"
Requires-Dist: libtukaan-win (==0.1.2) ; sys_platform == "win32"
